Fryday/Fryday.py
Fryday/__init__.py
Fryday/Database/__init__.py
Fryday/Database/Documents/__init__.py
Fryday/Database/Instagram/__init__.py
Fryday/Database/Youtube/__init__.py
Fryday/Database/screenshots/__init__.py
fridayAI-0.0.3.dist-info/LICENSE
fridayAI-0.0.3.dist-info/METADATA
fridayAI-0.0.3.dist-info/WHEEL
fridayAI-0.0.3.dist-info/top_level.txt
fridayAI-0.0.3.dist-info/RECORD
