Metadata-Version: 2.1
Name: fridayAI
Version: 0.0.3
Summary: fridayAI
Home-page: UNKNOWN
Author: Sam
Author-email: sam06eer@gmail.com
License: UNKNOWN
Keywords: assistant,AI,Virtual,python
Platform: UNKNOWN
Classifier: Development Status :: 1 - Planning
Classifier: Intended Audience :: Developers
Classifier: Programming Language :: Python :: 3
Classifier: Operating System :: Microsoft :: Windows
License-File: LICENSE
Requires-Dist: opencv-python
Requires-Dist: Pyaudio
Requires-Dist: pyttsx3
Requires-Dist: SpeechRecognition
Requires-Dist: keyboard
Requires-Dist: instaloader
Requires-Dist: wikipedia
Requires-Dist: wolframalpha
Requires-Dist: selenium
Requires-Dist: pyautogui
Requires-Dist: pywikihow
Requires-Dist: PyPDF2
Requires-Dist: twilio
Requires-Dist: pywhatkit
Requires-Dist: googletrans
Requires-Dist: google-trans-new
Requires-Dist: geopy
Requires-Dist: geocoder
Requires-Dist: win10toast
